EulerFlow/AnalyticalTvNS.py
EulerFlow/BoundaryConditions.py
EulerFlow/DiffusionSol1D.py
EulerFlow/DiffusionSol2D.py
EulerFlow/EulerSol1D.py
EulerFlow/EulerSolQuasi1D.py
EulerFlow/JamesonShmidtTurkel.py
EulerFlow/Sedov1D.py
EulerFlow/WaveEqn1D.py
EulerFlow/WaveEqn1DAMR.py
EulerFlow/__init__.py
EulerFlow/mathutils.py
EulerFlow/propagate1dr.py
EulerFlow/taylorNeumannSedov.py
EulerFlow/analytic/sedovAnalticSol.py
pyflowsolver-0.3.4.dist-info/licenses/LICENSE
pyflowsolver-0.3.4.dist-info/METADATA
pyflowsolver-0.3.4.dist-info/WHEEL
pyflowsolver-0.3.4.dist-info/top_level.txt
pyflowsolver-0.3.4.dist-info/RECORD
