Metadata-Version: 2.4
Name: PyFlowSolver
Version: 0.3.4
Summary: Solve the Euler Equations for inviscid compressible flow in 1D.
Author-email: Hugh Morgan <serebrum@gmail.com>
Maintainer-email: Hugh Morgan <serebrum@gmail.com>
License:                     GNU GENERAL PUBLIC LICENSE
Project-URL: homepage, https://github.com/taylorhughmorgan/EulerFlow
Keywords: Euler,Navier-Stokes,PDE,Flow,Compressible,ODE
Requires-Python: >=3.8
License-File: LICENSE
Requires-Dist: numpy
Requires-Dist: matplotlib
Requires-Dist: scipy
Dynamic: license-file
